{"name":"build-javascript","namedChunkGroups":{"polyfill":{"name":"polyfill","assets":[{"name":"webpack-runtime-469c440eda6f91bd9f78.js","size":3911},{"name":"polyfill-60dd0d2f966a238f58ec.js","size":85854}],"filteredAssets":0,"assetsSize":89765,"filteredAuxiliaryAssets":2,"auxiliaryAssetsSize":223740},"app":{"name":"app","assets":[{"name":"webpack-runtime-469c440eda6f91bd9f78.js","size":3911},{"name":"framework-23c70297eb596e058021.js","size":129758},{"name":"532a2f07-6fc62f65a4e152617cf7.js","size":239073},{"name":"app-a5d47d614380a4f32e4f.js","size":78339}],"filteredAssets":0,"assetsSize":451081,"filteredAuxiliaryAssets":4,"auxiliaryAssetsSize":1169765},"component---src-pages-404-js":{"name":"component---src-pages-404-js","assets":[{"name":"component---src-pages-404-js-6af9b079ab2850fff743.js","size":820}],"filteredAssets":0,"assetsSize":820,"filteredAuxiliaryAssets":1,"auxiliaryAssetsSize":1997},"component---src-pages-blog-js":{"name":"component---src-pages-blog-js","assets":[{"name":"component---src-pages-blog-js-bd397920331492ba1f57.js","size":322}],"filteredAssets":0,"assetsSize":322,"filteredAuxiliaryAssets":1,"auxiliaryAssetsSize":729},"component---src-pages-index-js":{"name":"component---src-pages-index-js","assets":[{"name":"component---src-pages-index-js-806f83e671020745c5c2.js","size":321}],"filteredAssets":0,"assetsSize":321,"filteredAuxiliaryAssets":1,"auxiliaryAssetsSize":422}},"assetsByChunkName":{"polyfill":["webpack-runtime-469c440eda6f91bd9f78.js","polyfill-60dd0d2f966a238f58ec.js"],"app":["webpack-runtime-469c440eda6f91bd9f78.js","framework-23c70297eb596e058021.js","532a2f07-6fc62f65a4e152617cf7.js","app-a5d47d614380a4f32e4f.js"],"component---src-pages-404-js":["component---src-pages-404-js-6af9b079ab2850fff743.js"],"component---src-pages-blog-js":["component---src-pages-blog-js-bd397920331492ba1f57.js"],"component---src-pages-index-js":["component---src-pages-index-js-806f83e671020745c5c2.js"]},"childAssetsByChunkName":{}}